LICENSE
MANIFEST.in
README.md
setup.py
pyShelly/__init__.py
pyShelly/base.py
pyShelly/block.py
pyShelly/cloud.py
pyShelly/coap.py
pyShelly/compat.py
pyShelly/const.py
pyShelly/debug.py
pyShelly/device.py
pyShelly/dimmer.py
pyShelly/firmware.py
pyShelly/light.py
pyShelly/loop.py
pyShelly/mdns.py
pyShelly/mqtt.py
pyShelly/mqtt_client.py
pyShelly/mqtt_server.py
pyShelly/powermeter.py
pyShelly/relay.py
pyShelly/roller.py
pyShelly/sensor.py
pyShelly/switch.py
pyShelly/trv.py
pyShelly/utils.py
pyShelly/ws_client.py
pyShellyEx.egg-info/PKG-INFO
pyShellyEx.egg-info/SOURCES.txt
pyShellyEx.egg-info/dependency_links.txt
pyShellyEx.egg-info/requires.txt
pyShellyEx.egg-info/top_level.txt