Metadata-Version: 2.1
Name: pyShellyEx
Version: 1.0.2
Summary: Library for Shelly smart home devices (Modified version)
Home-page: https://github.com/GoNzCiD/pyShelly
Author: StyraHem / Tarra AB
Author-email: info@styrahem.se
License: MIT
Platform: UNKNOWN
Classifier: Programming Language :: Python :: 2.7
Classifier: Programming Language :: Python :: 3
Classifier: License :: OSI Approved :: MIT License
Classifier: Operating System :: OS Independent
